MANIFEST.in
README.md
requirements.txt
setup.cfg
setup.py
face_scrambler/__init__.py
face_scrambler/__main__.py
face_scrambler/func_dump.py
face_scrambler/gui.py
face_scrambler/gui2.py
face_scrambler/helpers.py
face_scrambler/scrambler.py
face_scrambler/ui_tests.py
face_scrambler.egg-info/PKG-INFO
face_scrambler.egg-info/SOURCES.txt
face_scrambler.egg-info/dependency_links.txt
face_scrambler.egg-info/entry_points.txt
face_scrambler.egg-info/top_level.txt