Metadata-Version: 1.1
Name: face-scrambler
Version: 0.0.1
Summary: Python package that scrambles an elliptical section of images.
Home-page: https://github.com/Foucl/face_scrambler
Author: Christopher Dannheim
Author-email: ch.dannheim@gmail.com
License: BSD
Download-URL: https://github.com/Foucl/face_scrambler/tarball/0.0.1
Platform: UNKNOWN
Classifier: Development Status :: 3 - Alpha
Classifier: Intended Audience :: Developers
Classifier: Programming Language :: Python :: 2.7
